torch_motion_correction/__init__.py
torch_motion_correction/correct_motion.py
torch_motion_correction/data_io.py
torch_motion_correction/deformation_field_utils.py
torch_motion_correction/estimate_motion_optimizer.py
torch_motion_correction/estimate_motion_xc.py
torch_motion_correction/optimization_state.py
torch_motion_correction/patch_utils.py
torch_motion_correction/py.typed
torch_motion_correction/utils.py
torch_motion_correction/patch_grid/__init__.py
torch_motion_correction/patch_grid/_patch_grid.py
torch_motion_correction/patch_grid/_patch_grid_centers.py
torch_motion_correction/patch_grid/_patch_grid_indices.py
torch_motion_correction-0.0.5.dist-info/METADATA
torch_motion_correction-0.0.5.dist-info/WHEEL
torch_motion_correction-0.0.5.dist-info/licenses/LICENSE
torch_motion_correction-0.0.5.dist-info/RECORD
